Lab02/gcd.v
//`timescale 1ns / 1ps
module GCD (
  input wire CLK,
  input wire RST_N,
  input wire [7:0] A,
  input wire [7:0] B,
  input wire START,
  output reg [7:0] Y,
  output reg DONE,
  output reg ERROR
);

wire found;
reg [7:0] reg_a, reg_b, next_a, next_b, Y_next;
reg [7:0] big_one;
reg error_next;
reg [1:0] state, state_next;

parameter [1:0] IDLE = 2'b00;
parameter [1:0] CALC = 2'b01;
parameter [1:0] FINISH = 2'b10;
/// Implementation below ///
/// update ERROR ///
always@(posedge CLK) begin
  if (RST_N == 1'b0)  ERROR <= 0;
  else  ERROR <= error_next;
end

/// reset actions ///
always@(posedge CLK) begin
  if (RST_N == 1'b0) begin
    state <= IDLE;
    Y <= 1'b0;
  end
  else
    state <= state_next;
end

/// wire found -> use assign ///
assign found = (next_a == 0 || next_b == 0) ? 1 : 0;

/// FSM ///
always@* begin
  case(state)
    IDLE: begin
      DONE = 0;
      ERROR = 0;
      if (START) begin
        state_next = CALC;
        error_next = (A == 0 || B == 0);
        reg_a = A;
        reg_b = B;
      end
      else begin
        state_next = IDLE;
        error_next = 0;
      end
    end
    CALC: begin
      /// big_one initialization ///
      if (big_one)  big_one = big_one;
      else  big_one = 0;
      ///
      if (!found && !ERROR) begin
        state_next = CALC;
        error_next = ERROR;
      end
      else begin
        state_next = FINISH;
        error_next = ERROR;
      end
    end
    FINISH: begin
      state_next = IDLE;
      error_next = 0;
      DONE = 1;
    end
    default:
      state_next = state_next;
  endcase
end

/// update reg_a, reg_b ///
always@(posedge CLK) begin
  if (state == CALC) begin
    reg_a <= next_a;
    reg_b <= next_b;
  end
end

/// perform SUB ///
always@* begin
  if (state == CALC) begin 
    if (reg_a > reg_b) begin
      next_a = reg_a - reg_b;
      next_b = reg_b;
    end
    else begin
      next_b = reg_b - reg_a;
      next_a = reg_a;
    end
  end  
end

/// chosing big_one ///
always@* begin
  if(state == CALC) begin
    if (next_a == 8'd0) begin
      big_one = next_b;
    end
    else if (next_b == 8'd0) begin
      big_one = next_a;
    end
    else begin
      big_one = big_one;
    end
  end
  else begin
    big_one = big_one;
  end
end

/// update Y_next ///
always@* begin
  if(state == CALC) begin
    Y_next = big_one;
  end
  else if (state == FINISH) begin
    Y_next = Y;
  end
  else begin
    Y_next = Y_next;
  end
end

/// update Y ///
always@(posedge CLK) begin
  if (RST_N == 1'b0) begin
    Y_next <= 8'b0;
    Y <= Y_next;
  end
  else
    Y <= Y_next;
end
///
endmodule

Lab02/gcd_t.v
`timescale 1ns/1ps
module stimulus;
  parameter cyc = 40;
  parameter delay = 4;

  reg clk, rst_n, start;
  reg [7:0] a, b;
  wire done, error;
  wire [7:0] y;

  integer latency;
  integer start_time, end_time;
  reg  start_flag = 1'b0;

  GCD gcd01 (
    .CLK(clk),
    .RST_N(rst_n),
    .A(a),
    .B(b),
    .START(start),
    .Y(y),
    .DONE(done),
    .ERROR(error)
  );

  always #(cyc/2) clk = ~clk;

  initial begin
`ifdef SYNTHESIS
    $sdf_annotate("gcd_syn.sdf", gcd01);
    $dumpfile("gcd_syn.vcd");
`else
    $dumpfile("gcd.vcd");
`endif
    $dumpvars;

    $monitor($time, " CLK=%b RST_N=%b START=%b A=%d B=%d | DONE=%b Y=%d ERROR=%b",
      clk, rst_n, start, a, b, done, y, error);
  end


  initial begin
    clk = 1;
    rst_n = 1;
    nop;
    data_in(0,0);
    #(cyc);
    #(delay) rst_n = 0;
    #(cyc*4) rst_n = 1;
//    #(cyc/2*5+delay) rst_n = 1;
//    #(cyc/2-delay);
    #(cyc*2);

    #(cyc) nop;

    #(cyc) load; data_in(8'd21, 8'd6);
    #(cyc) nop;
    @(posedge done); #(delay);
    
    #(cyc) load; data_in(8'd8, 8'd17);
    #(cyc) nop;
    @(posedge done); #(delay);

    #(cyc) load; data_in(8'd35, 8'd0);
    #(cyc) nop;
    @(posedge done); #(delay);

    #(cyc) load; data_in(8'd42, 8'd42);
    #(cyc) nop;
    @(posedge done); #(delay);

    #(cyc) load; data_in(8'd0, 8'd0);
    #(cyc) nop;
    @(posedge done); 


    #(cyc) nop;
    #(cyc*8);
//    $display("start: %d, end: %d", start_time, end_time);
    latency = (end_time - start_time)/cyc;
    $display("Latency: %d cycle(s)", latency);
    $finish;
  end

  always @(posedge clk) begin
    if (start == 1'b1) begin
      if (start_flag == 1'b0) begin
        start_flag = 1'b1;
        start_time = $time;
      end
    end
    if (done == 1'b1) begin
      end_time = $time;
    end
  end

  // tasks
  task nop;
    begin
      start = 0;
    end
  endtask
  task load;
    begin
      start = 1;
    end
  endtask
  task data_in;
    input [7:0] data1, data2;
    begin
      a = data1;
      b = data2;
    end
  endtask

endmodule

Lab02/gcd.vcd
$date
	Sat May 22 16:09:01 2021
$end
$version
	Icarus Verilog
$end
$timescale
	1ps
$end
$scope module stimulus $end
$var wire 8 ! y [7:0] $end
$var wire 1 " error $end
$var wire 1 # done $end
$var reg 8 $ a [7:0] $end
$var reg 8 % b [7:0] $end
$var reg 1 & clk $end
$var reg 1 ' rst_n $end
$var reg 1 ( start $end
$var reg 1 ) start_flag $end
$var integer 32 * end_time [31:0] $end
$var integer 32 + latency [31:0] $end
$var integer 32 , start_time [31:0] $end
$scope module gcd01 $end
$var wire 8 - A [7:0] $end
$var wire 8 . B [7:0] $end
$var wire 1 & CLK $end
$var wire 1 ' RST_N $end
$var wire 1 ( START $end
$var wire 1 / found $end
$var reg 1 # DONE $end
$var reg 1 " ERROR $end
$var reg 8 0 Y [7:0] $end
$var reg 8 1 Y_next [7:0] $end
$var reg 8 2 big_one [7:0] $end
$var reg 1 3 error_next $end
$var reg 8 4 next_a [7:0] $end
$var reg 8 5 next_b [7:0] $end
$var reg 8 6 reg_a [7:0] $end
$var reg 8 7 reg_b [7:0] $end
$var reg 2 8 state [1:0] $end
$var reg 2 9 state_next [1:0] $end
$upscope $end
$scope task data_in $end
$var reg 8 : data1 [7:0] $end
$var reg 8 ; data2 [7:0] $end
$upscope $end
$scope task load $end
$upscope $end
$scope task nop $end
$upscope $end
$upscope $end
$enddefinitions $end
#0
$dumpvars
b0 ;
b0 :
bx 9
bx 8
bx 7
bx 6
bx 5
bx 4
x3
bx 2
bx 1
bx 0
x/
b0 .
b0 -
bx ,
bx +
bx *
0)
0(
1'
1&
b0 %
b0 $
x#
x"
bx !
$end
#20000
0&
#40000
1&
#44000
0'
#60000
0&
#80000
03
b0 9
0#
0"
b0 !
b0 0
b0 8
b0 1
1&
#100000
0&
#120000
1&
#140000
0&
#160000
1&
#180000
0&
#200000
1&
#204000
1'
#220000
0&
#240000
1&
#260000
0&
#280000
1&
#300000
0&
#320000
1&
#340000
0&
#360000
1&
#364000
b110 7
b10101 6
b1 9
b110 %
b110 .
b10101 $
b10101 -
b110 ;
b10101 :
1(
#380000
0&
#400000
0/
b110 5
b1111 4
b1 9
b0 2
b1 8
b110010000 ,
1)
1&
#404000
0(
#420000
0&
#440000
b1001 4
b1111 6
1&
#460000
0&
#480000
b11 4
b1001 6
1&
#500000
0&
#520000
b11 5
b11 6
1&
#540000
0&
#560000
b10 9
1/
b11 1
b11 2
b0 5
b11 7
1&
#580000
0&
#600000
1#
b0 9
b11 !
b11 0
b0 7
b10 8
1&
#620000
0&
#640000
0#
b0 8
b1010000000 *
1&
#644000
b10001 7
b1000 6
b1 9
b10001 %
b10001 .
b1000 $
b1000 -
b10001 ;
b1000 :
1(
#660000
0&
#680000
0/
b1000 4
b1001 5
b1 9
b1 8
1&
#684000
0(
#700000
0&
#720000
b1 5
b1001 7
1&
#740000
0&
#760000
b111 4
b1 7
1&
#780000
0&
#800000
b110 4
b111 6
1&
#820000
0&
#840000
b101 4
b110 6
1&
#860000
0&
#880000
b100 4
b101 6
1&
#900000
0&
#920000
b11 4
b100 6
1&
#940000
0&
#960000
b10 4
b11 6
1&
#980000
0&
#1000000
b1 4
b10 6
1&
#1020000
0&
#1040000
b10 9
1/
b1 1
b1 2
b0 5
b1 6
1&
#1060000
0&
#1080000
1#
b0 9
b1 !
b1 0
b0 7
b10 8
1&
#1100000
0&
#1120000
0#
b0 8
b10001100000 *
1&
#1124000
b100011 6
13
b1 9
b0 %
b0 .
b100011 $
b100011 -
b0 ;
b100011 :
1(
#1140000
0&
#1160000
b100011 1
b100011 2
b100011 4
b10 9
b1 8
1"
1&
#1164000
0(
#1180000
0&
#1200000
1#
03
b0 9
b10 8
b100011 !
b100011 0
1&
#1220000
0&
#1240000
0#
b0 8
0"
b10011011000 *
1&
#1244000
b101010 7
b101010 6
b1 9
b101010 %
b101010 .
b101010 $
b101010 -
b101010 ;
b101010 :
1(
#1260000
0&
#1280000
b101010 1
b101010 2
b101010 4
b10 9
b1 8
1&
#1284000
0(
#1300000
0&
#1320000
1#
b0 9
b101010 !
b101010 0
b0 7
b10 8
1&
#1340000
0&
#1360000
0#
b0 8
b10101010000 *
1&
#1364000
b0 6
13
b1 9
b0 %
b0 .
b0 $
b0 -
b0 ;
b0 :
1(
#1380000
0&
#1400000
b0 1
b0 2
b0 4
b10 9
b1 8
1"
1&
#1404000
0(
#1420000
0&
#1440000
1#
03
b0 9
b10 8
b0 !
b0 0
1&
#1460000
0&
#1480000
0#
b0 8
0"
b10111001000 *
1&
#1500000
0&
#1520000
1&
#1540000
0&
#1560000
1&
#1580000
0&
#1600000
1&
#1620000
0&
#1640000
1&
#1660000
0&
#1680000
1&
#1700000
0&
#1720000
1&
#1740000
0&
#1760000
1&
#1780000
0&
#1800000
1&
b11011 +
